{"userProfileId": 113344557, "totalKilocalories": 2936.0, "activeKilocalories": 905.0, "bmrKilocalories": 2031.0, "wellnessKilocalories": 2936.0, "burnedKilocalories": null, "consumedKilocalories": null, "remainingKilocalories": 2936.0, "totalSteps": 5860, "netCalorieGoal": 2120, "totalDistanceMeters": 3876, "wellnessDistanceMeters": 3876, "wellnessActiveKilocalories": 905.0, "netRemainingKilocalories": 3025.0, "userDailySummaryId": 113344557, "calendarDate": "2023-08-09", "rule": {"typeId": 3, "typeKey": "subscribers"}, "uuid": "604615c8039942829111ab2c5cc62534", "dailyStepGoal": 5000, "wellnessStartTimeGmt": "2023-08-08T21:00:00.0", "wellnessStartTimeLocal": "2023-08-09T00:00:00.0", "wellnessEndTimeGmt": "2023-08-09T21:00:00.0", "wellnessEndTimeLocal": "2023-08-10T00:00:00.0", "durationInMilliseconds": 86400000, "wellnessDescription": null, "highlyActiveSeconds": 657, "activeSeconds": 8850, "sedentarySeconds": 55713, "sleepingSeconds": 21180, "includesWellnessData": true, "includesActivityData": true, "includesCalorieConsumedData": false, "privacyProtected": false, "moderateIntensityMinutes": 93, "vigorousIntensityMinutes": 14, "floorsAscendedInMeters": 61.294, "floorsDescendedInMeters": 36.58, "floorsAscended": 20.10958, "floorsDescended": 12.00131, "intensityMinutesGoal": 150, "userFloorsAscendedGoal": 10, "minHeartRate": 51, "maxHeartRate": 150, "restingHeartRate": 52, "lastSevenDaysAvgRestingHeartRate": 54, "source": "GARMIN", "averageStressLevel": 39, "maxStressLevel": 99, "stressDuration": 32880, "restStressDuration": 26640, "activityStressDuration": 18300, "uncategorizedStressDuration": 7140, "totalStressDuration": 84960, "lowStressDuration": 7260, "mediumStressDuration": 20220, "highStressDuration": 5400, "stressPercentage": 38.7, "restStressPercentage": 31.36, "activityStressPercentage": 21.54, "uncategorizedStressPercentage": 8.4, "lowStressPercentage": 8.55, "mediumStressPercentage": 23.8, "highStressPercentage": 6.36, "stressQualifier": "STRESSFUL", "measurableAwakeDuration": 56820, "measurableAsleepDuration": 21000, "lastSyncTimestampGMT": null, "minAvgHeartRate": 52, "maxAvgHeartRate": 148, "bodyBatteryChargedValue": 64, "bodyBatteryDrainedValue": 96, "bodyBatteryHighestValue": 96, "bodyBatteryLowestValue": 12, "bodyBatteryMostRecentValue": 12, "bodyBatteryDuringSleep": null, "bodyBatteryVersion": 2.0, "abnormalHeartRateAlertsCount": null, "averageSpo2": null, "lowestSpo2": null, "latestSpo2": null, "latestSpo2ReadingTimeGmt": null, "latestSpo2ReadingTimeLocal": null, "averageMonitoringEnvironmentAltitude": 119.0, "restingCaloriesFromActivity": 174.0, "avgWakingRespirationValue": 13.0, "highestRespirationValue": 17.0, "lowestRespirationValue": 10.0, "latestRespirationValue": 15.0, "latestRespirationTimeGMT": "2023-08-09T21:00:00.0"}