{"userProfileId": 113344557, "totalKilocalories": 2261.0, "activeKilocalories": 200.0, "bmrKilocalories": 2061.0, "wellnessKilocalories": 2261.0, "burnedKilocalories": null, "consumedKilocalories": null, "remainingKilocalories": 2261.0, "totalSteps": 6688, "netCalorieGoal": 1900, "totalDistanceMeters": 5428, "wellnessDistanceMeters": 5428, "wellnessActiveKilocalories": 200.0, "netRemainingKilocalories": 2100.0, "userDailySummaryId": 113344557, "calendarDate": "2023-11-24", "rule": {"typeId": 3, "typeKey": "subscribers"}, "uuid": "2b276e8c531f474e83e7cf86cf85b535", "dailyStepGoal": 6710, "wellnessStartTimeGmt": "2023-11-23T21:00:00.0", "wellnessStartTimeLocal": "2023-11-24T00:00:00.0", "wellnessEndTimeGmt": "2023-11-24T21:00:00.0", "wellnessEndTimeLocal": "2023-11-25T00:00:00.0", "durationInMilliseconds": 86400000, "wellnessDescription": null, "highlyActiveSeconds": 353, "activeSeconds": 5416, "sedentarySeconds": 66531, "sleepingSeconds": 14100, "includesWellnessData": true, "includesActivityData": false, "includesCalorieConsumedData": false, "privacyProtected": false, "moderateIntensityMinutes": 0, "vigorousIntensityMinutes": 0, "floorsAscendedInMeters": 56.604, "floorsDescendedInMeters": 44.664, "floorsAscended": 18.57087, "floorsDescended": 14.65354, "intensityMinutesGoal": 150, "userFloorsAscendedGoal": 10, "minHeartRate": 53, "maxHeartRate": 116, "restingHeartRate": 54, "lastSevenDaysAvgRestingHeartRate": 54, "source": "GARMIN", "averageStressLevel": 30, "maxStressLevel": 81, "stressDuration": 33240, "restStressDuration": 30300, "activityStressDuration": 8760, "uncategorizedStressDuration": 13980, "totalStressDuration": 86280, "lowStressDuration": 23400, "mediumStressDuration": 9480, "highStressDuration": 360, "stressPercentage": 38.53, "restStressPercentage": 35.12, "activityStressPercentage": 10.15, "uncategorizedStressPercentage": 16.2, "lowStressPercentage": 27.12, "mediumStressPercentage": 10.99, "highStressPercentage": 0.42, "stressQualifier": "BALANCED", "measurableAwakeDuration": 58200, "measurableAsleepDuration": 14100, "lastSyncTimestampGMT": null, "minAvgHeartRate": 53, "maxAvgHeartRate": 114, "bodyBatteryChargedValue": 76, "bodyBatteryDrainedValue": 61, "bodyBatteryHighestValue": 81, "bodyBatteryLowestValue": 9, "bodyBatteryMostRecentValue": 27, "bodyBatteryDuringSleep": null, "bodyBatteryVersion": 2.0, "abnormalHeartRateAlertsCount": null, "averageSpo2": null, "lowestSpo2": null, "latestSpo2": null, "latestSpo2ReadingTimeGmt": null, "latestSpo2ReadingTimeLocal": null, "averageMonitoringEnvironmentAltitude": 165.0, "restingCaloriesFromActivity": null, "avgWakingRespirationValue": 14.0, "highestRespirationValue": 20.0, "lowestRespirationValue": 6.0, "latestRespirationValue": 13.0, "latestRespirationTimeGMT": "2023-11-24T21:00:00.0"}